# 符号引用与直接引用怎么理解

## 核心概念

符号引用和直接引用是 JVM 类加载和动态链接过程中的两个核心概念，描述了方法调用和字段访问在不同阶段的引用形式。符号引用是编译期的字面量描述，与 JVM 内存布局无关；直接引用是运行期指向目标的指针、偏移量或句柄，与 JVM 内存布局相关。

理解两者的关键是知道类加载的解析阶段：把常量池中的符号引用替换为直接引用。这一步是 Java 实现"运行时绑定"的基础。

```text
编译期：源码 → javac → Class 文件常量池（符号引用）
                              ↓ 类加载解析阶段
运行期：JVM 内存（直接引用：指针/偏移量/句柄）
```

## 标准回答

符号引用是 Class 文件常量池中的字面量描述（如 `java/lang/Object.toString:()Ljava/lang/String;`），与 JVM 内存布局无关，引用目标不一定已加载。直接引用是指向目标的指针、偏移量或句柄，与 JVM 内存布局相关，引用目标必须已在内存中。在类加载的解析阶段，JVM 把符号引用替换为直接引用。

要点：

1. **符号引用**：编译期生成，存于 Class 文件常量池；与内存布局无关。
2. **直接引用**：解析阶段生成，存于 JVM 内存；与内存布局相关。
3. **转换时机**：类加载的解析阶段，部分引用延迟到首次使用时（运行时绑定）。
4. **静态绑定**：编译期可知的方法（static、private、final、构造方法）在解析阶段直接转换。
5. **动态绑定**：虚方法（普通实例方法）在运行时根据对象实际类型解析。

## 符号引用

符号引用用一组符号描述引用目标，可以是任何字面量。包含三类：

- **类和接口的全限定名**：`java/lang/String`
- **字段的名称和描述符**：`name:Ljava/lang/String;`
- **方法的名称和描述符**：`toString:()Ljava/lang/String;`

特点：

- 与 JVM 内存布局无关。
- 引用目标不一定已加载到内存。
- 在编译期生成，存于 Class 文件常量池。
- JVM 规范不规定符号引用的具体格式，由 JVM 实现决定。

示例：

```text
// javap 输出的常量池项
#1 = Methodref          #4.#18   // java/lang/Object."<init>":()V
#2 = Fieldref           #3.#19   // com/example/Main.m:I
#18 = NameAndType       #7:#8    // "<init>":()V
```

`#1` 是一个方法引用，由 `#4`（类）和 `#18`（NameAndType）组成，最终描述 `java/lang/Object.<init>:()V`，这就是符号引用。

## 直接引用

直接引用是能直接指向目标的指针、相对偏移量或句柄。

特点：

- 与 JVM 内存布局相关。
- 引用目标必须已在内存中。
- 在解析阶段生成。
- 形式由 JVM 实现决定：可以是直接指针、偏移量，或句柄。

示例：

- 类的直接引用：指向方法区中类元数据的指针。
- 字段的直接引用：字段在对象中的偏移量。
- 方法的直接引用：方法入口地址，或虚方法表中的索引。

## 转换过程

解析阶段（Resolution）是类加载链接的一部分，把常量池中的符号引用替换为直接引用。

```text
类加载生命周期：
加载 → 验证 → 准备 → 解析 → 初始化
                       ↑
                  符号引用 → 直接引用
```

| 阶段 | 操作 |
|------|------|
| 加载 | 读取 Class 文件，创建 Class 对象，引用仍为符号 |
| 验证 | 确保符号引用的正确性 |
| 准备 | 为类变量分配内存并赋零值 |
| 解析 | 把符号引用替换为直接引用 |
| 初始化 | 执行 `<clinit>` |

JVM 不要求解析阶段一定在初始化前完成，有些引用可以延迟到首次使用时解析，称为延迟解析或运行时绑定。

## 静态绑定 vs 动态绑定

### 静态绑定（早期绑定）

编译期可知、运行期不变的方法在解析阶段直接转换为直接引用。包括：

- 静态方法（`invokestatic`）
- 私有方法（`invokespecial`）
- 实例构造器 `<init>`（`invokespecial`）
- 父类方法（`invokespecial`）
- final 方法（`invokevirtual`，但因不可覆盖，按静态处理）

这些方法称为"非虚方法"。

### 动态绑定（晚期绑定）

虚方法（普通实例方法）在运行时根据对象实际类型解析，称为"虚方法"。

```java
class Animal { void speak() { System.out.println("animal"); } }
class Dog extends Animal { @Override void speak() { System.out.println("dog"); } }

Animal a = new Dog();
a.speak(); // 运行时根据 a 的实际类型 Dog 解析，调用 Dog.speak
```

JVM 通过虚方法表（vtable）实现动态绑定：每个类有一个虚方法表，存放方法的实际入口。`invokevirtual` 时先查对象的实际类型的 vtable，得到方法入口。

## 异常情况

解析阶段如果找不到目标，JVM 抛出：

- `NoClassDefFoundError`：类未找到。
- `NoSuchFieldError`：字段未找到。
- `NoSuchMethodError`：方法未找到。
- `IllegalAccessError`：访问权限不足。

## 代码示例

观察符号引用：

```java
public class SymbolRefDemo {
    public static void main(String[] args) {
        Object o = new Object();
        String s = o.toString();
    }
}
```

`javap -v SymbolRefDemo.class`：

```text
Constant pool:
   #1 = Methodref          #4.#18    // java/lang/Object."<init>":()V
   #2 = Methodref          #3.#19    // SymbolRefDemo.main:([Ljava/lang/String;)V
   #3 = Class              #20       // SymbolRefDemo
   #4 = Class              #21       // java/lang/Object
   ...
  #18 = NameAndType        #7:#8     // "<init>":()V
  #19 = NameAndType        #9:#10    // main:([Ljava/lang/String;)V
  #20 = Utf8               SymbolRefDemo
  #21 = Utf8               java/lang/Object

public static void main(java.lang.String[]);
    Code:
       0: new           #4      // class java/lang/Object
       3: dup
       4: invokespecial #1      // Method java/lang/Object."<init>":()V
       7: astore_1
       8: aload_1
       9: invokevirtual #5      // Method java/lang/Object.toString:()Ljava/lang/String;
```

字节码中的 `#1`、`#4`、`#5` 等都是常量池索引，引用的是符号引用。运行时 `invokevirtual` 通过动态绑定查 vtable 找到方法入口（直接引用）。

## 实战场景

| 场景 | 表现 | 排查 |
|------|------|------|
| 版本不兼容 | 删除了某方法，旧 jar 调用时 `NoSuchMethodError` | 检查依赖版本 |
| 类冲突 | 同一类被不同 ClassLoader 加载，互相不可见 | 检查类隔离 |
| 反射调用慢 | 反射每次都要查找直接引用 | 缓存 Method 对象 |
| JIT 内联 | final 方法静态绑定，JIT 可内联 | 提示 JIT 优化 |

## 深挖追问

### 符号引用和直接引用的转换什么时候发生？

主要在类加载的解析阶段。但 JVM 允许延迟解析：某些引用（如虚方法）在首次使用时才解析。这种延迟解析是 Java 实现运行时绑定的基础。

### 虚方法表是什么？

虚方法表（vtable）是每个类的虚方法入口表，存放方法的实际入口地址。`invokevirtual` 时先获取对象的实际类型，查该类型的 vtable，得到方法入口。vtable 在类加载的连接阶段初始化，子类 vtable 继承父类 vtable，覆盖的方法替换入口。

### 为什么 final 方法是静态绑定？

final 方法不可被子类覆盖，调用入口在编译期唯一确定，不需要运行时查 vtable。JIT 还可以把 final 方法内联到调用点，消除方法调用开销。

### 反射为什么慢？

`Method.invoke` 每次都要：

1. 检查访问权限。
2. 解析符号引用到直接引用（首次）。
3. 装箱拆箱参数。
4. 通过 native 调用方法。

JDK 内部对反射做了大量优化（MethodAccessor、GeneratedMethodAccessor），但仍比直接调用慢几倍。建议缓存 Method 对象，避免重复查找。

## 易错点

- 把符号引用当作"代码中的字符串"，实际是 Class 文件常量池中的字面量。
- 以为所有方法都是动态绑定，静态方法、私有方法、final 方法是静态绑定。
- 以为解析阶段必须发生在初始化前，JVM 允许延迟解析。
- 把"动态绑定"和"反射"混淆，动态绑定是 invokevirtual 通过 vtable 查找，反射是 `Method.invoke`。
- 以为 `NoSuchMethodError` 是编译期错误，实际是运行期错误，发生在解析阶段。

## 总结

符号引用是 Class 文件常量池中的字面量描述，与内存布局无关；直接引用是指向目标的指针/偏移量/句柄，与内存布局相关。类加载的解析阶段把符号引用转换为直接引用。静态方法、私有方法、final 方法是静态绑定（编译期可知），普通实例方法是动态绑定（运行时通过 vtable 查找）。理解两者是阅读字节码、排查 NoSuchMethodError、理解反射性能的基础。

## 参考资料

- [JVM Specification - Resolution](https://docs.oracle.com/javase/specs/jvms/se17/html/jvms-5.html#jvms-5.4.3)
- 《深入理解 Java 虚拟机》周志明 第 7 章
- [Dynamic Linking in JVM](https://www.artima.com/insidejvm/ed2/linkmod.html)

---

[← 返回 JVM 基础目录](/01-java-core/jvm/basics/)
